LICENSE
README.md
setup.cfg
setup.py
SSEM/SSEM.py
SSEM/__init__.py
SSEM.egg-info/PKG-INFO
SSEM.egg-info/SOURCES.txt
SSEM.egg-info/dependency_links.txt
SSEM.egg-info/requires.txt
SSEM.egg-info/top_level.txt