Metadata-Version: 2.1
Name: SSEM
Version: 1.0
Summary: SSEM is a semantic similarity-based evaluation library for natural language processing (NLP) text generation tasks. It supports various similarity metrics and evaluation levels, and is compatible with any Hugging Face pre-trained transformer model.
Home-page: https://github.com/TechyNilesh/SSEM
Author: Nilesh Verma
Author-email: me@nileshverma.com
License: MIT
Download-URL: https://github.com/TechyNilesh/SSEM/archive/refs/tags/v_1.tar.gz
Keywords: Semantic similarity,SSEM,Evaluation metrics,NLP
Platform: UNKNOWN
Classifier: Development Status :: 4 - Beta
Classifier: Intended Audience :: Developers
Classifier: Topic :: Software Development :: Build Tools
Classifier: License :: OSI Approved :: MIT License
Classifier: Programming Language :: Python :: 3
Classifier: Programming Language :: Python :: 3.7
Classifier: Programming Language :: Python :: 3.8
Classifier: Programming Language :: Python :: 3.9
Classifier: Programming Language :: Python :: 3.10
License-File: LICENSE
